pyversion_info/__init__.py
pyversion_info/__main__.py
pyversion_info/py.typed
pyversion_info/util.py
pyversion_info-1.2.4.dist-info/METADATA
pyversion_info-1.2.4.dist-info/WHEEL
pyversion_info-1.2.4.dist-info/entry_points.txt
pyversion_info-1.2.4.dist-info/licenses/LICENSE
pyversion_info-1.2.4.dist-info/RECORD
