Metadata-Version: 2.4
Name: pyversion-info
Version: 1.2.4
Summary: Get information about released & unreleased CPython and PyPy versions
Project-URL: Source Code, https://github.com/jwodder/pyversion-info
Project-URL: Bug Tracker, https://github.com/jwodder/pyversion-info/issues
Project-URL: Documentation, https://pyversion-info.readthedocs.io
Author-email: John Thorvald Wodder II <pyversion-info@varonathe.org>
License-Expression: MIT
License-File: LICENSE
Keywords: CPython,PyPy,history,python,python versions
Classifier: Intended Audience :: Developers
Classifier: Intended Audience :: Information Technology
Classifier: Intended Audience :: System Administrators
Classifier: Programming Language :: Python :: 3
Classifier: Programming Language :: Python :: 3 :: Only
Classifier: Programming Language :: Python :: 3.8
Classifier: Programming Language :: Python :: 3.9
Classifier: Programming Language :: Python :: 3.10
Classifier: Programming Language :: Python :: 3.11
Classifier: Programming Language :: Python :: 3.12
Classifier: Programming Language :: Python :: 3.13
Classifier: Programming Language :: Python :: Implementation :: CPython
Classifier: Programming Language :: Python :: Implementation :: PyPy
Classifier: Typing :: Typed
Requires-Python: >=3.8
Requires-Dist: cachecontrol[filecache]<0.15,>=0.12
Requires-Dist: click!=8.2.2,>=8.0
Requires-Dist: platformdirs<5.0,>=2.1
Requires-Dist: pydantic~=2.0
Requires-Dist: requests~=2.20
